python3_authjwt/__init__.py
python3_authjwt/auth.py
python3_authjwt-0.0.1.dist-info/LICENSE
python3_authjwt-0.0.1.dist-info/METADATA
python3_authjwt-0.0.1.dist-info/WHEEL
python3_authjwt-0.0.1.dist-info/top_level.txt
python3_authjwt-0.0.1.dist-info/RECORD
